frinZ/__init__.py
frinZ/cor.py
frinZ/test1.py
frinZ/test2.py
frinZ/test3.py
frinZ/utils.py
frinz-3.1.0.dist-info/licenses/LICENSE
frinz-3.1.0.dist-info/METADATA
frinz-3.1.0.dist-info/WHEEL
frinz-3.1.0.dist-info/top_level.txt
frinz-3.1.0.dist-info/RECORD
