Metadata-Version: 2.4
Name: frinZ
Version: 3.1.0
Summary: fringe search for Yamaguchi Interferometer and Japanese VLBI Network
Home-page: https://github.com/M-AKIMOTOO/frinZ.py
Author: Masanori AKIMOTO
Author-email: masanori.akimoto.ac@gmail.com
License: MIT
Classifier: Programming Language :: Python :: 3
Classifier: License :: OSI Approved :: MIT License
Classifier: Operating System :: OS Independent
Requires-Python: >=3.7
License-File: LICENSE
Dynamic: license-file
